nondeterminism/__init__.py
nondeterminism/main.py
nondeterminism-3.1.1.dist-info/METADATA
nondeterminism-3.1.1.dist-info/WHEEL
nondeterminism-3.1.1.dist-info/licenses/LICENSE.md
nondeterminism-3.1.1.dist-info/RECORD
