Metadata-Version: 2.4
Name: nondeterminism
Version: 3.1.1
Summary: A Python library for nondeterministic algorithms
Project-URL: homepage, https://aeporreca.org/nondeterminism
Project-URL: repository, https://github.com/aeporreca/nondeterminism.git
Project-URL: issues, https://github.com/aeporreca/nondeterminism/issues
Project-URL: documentation, https://aeporreca.org/nondeterminism
Author: Antonio E. Porreca, Greg Hamerly
Author-email: antonio.porreca@lis-lab.fr
License: LICENSE.md
License-File: LICENSE.md
Keywords: agpl,decorator,nondeterminism,nondeterministic-algorithms,python,python-library,python3
Classifier: License :: OSI Approved :: GNU Affero General Public License v3
Requires-Python: >=3.8
